pip_abandoned/__init__.py
pip_abandoned/__version__.py
pip_abandoned/cli.py
pip_abandoned/lib.py
pip_abandoned-0.4.1.dist-info/entry_points.txt
pip_abandoned-0.4.1.dist-info/LICENSE
pip_abandoned-0.4.1.dist-info/WHEEL
pip_abandoned-0.4.1.dist-info/METADATA
pip_abandoned-0.4.1.dist-info/RECORD
