Metadata-Version: 2.1
Name: pip-abandoned
Version: 0.4.1
Summary: Search for abandoned and deprecated python packages
Author-email: chris48s <git@chris-shaw.dev>
Requires-Python: >=3.8
Classifier: License :: OSI Approved :: MIT License
Classifier: Programming Language :: Python
Classifier: Programming Language :: Python :: 3
Classifier: Programming Language :: Python :: 3.8
Classifier: Programming Language :: Python :: 3.9
Classifier: Programming Language :: Python :: 3.10
Classifier: Programming Language :: Python :: 3.11
Classifier: Programming Language :: Python :: 3.12
Requires-Dist: keyring>=19
Requires-Dist: requests>=2,<3
Requires-Dist: rich>=12
Requires-Dist: importlib-metadata>=4.6; python_version < '3.10'
Requires-Dist: flit==3.9.0 ; extra == "dev"
Requires-Dist: isort==5.13.2 ; extra == "dev"
Requires-Dist: flake8==7.0.0 ; extra == "dev"
Requires-Dist: black==24.2.0 ; extra == "dev"
Requires-Dist: pytest==8.0.1 ; extra == "dev"
Requires-Dist: pytest-cov==4.1.0 ; extra == "dev"
Requires-Dist: responses==0.25.0 ; extra == "dev"
Project-URL: Home, https://github.com/chris48s/pip-abandoned
Project-URL: Source, https://github.com/chris48s/pip-abandoned
Provides-Extra: dev
